{
 "original_connector": "Clinical Trials",
 "tools": [
  {
   "description": "Analyze primary and secondary outcome measures (endpoints) from clinical trials.\n\nMODES (provide ONLY nct_id OR condition, not both):\n1. Single Trial: Provide nct_id ONLY to analyze one specific trial's endpoints\n2. Aggregate: Provide condition ONLY to analyze patterns across multiple trials\nIf both provided, nct_id takes precedence (single trial mode).\n\nSINGLE TRIAL MODE (nct_id):\n- Returns all endpoints for the specified trial\n- Useful for understanding specific trial design\n- Example: nct_id='NCT03661411'\n\nAGGREGATE MODE (condition):\n- Analyzes endpoints across many trials in a therapeutic area\n- Identifies common endpoint patterns and measures\n- Useful for protocol design and competitive analysis\n- Example: condition='diabetes', phase=['PHASE3']\n\nWHAT THIS RETURNS:\n- List of primary endpoints (main efficacy measures)\n- List of secondary endpoints (additional outcomes)\n- List of other endpoints (exploratory outcomes)\n- Most common measures across analyzed trials\n- Timeframes for each endpoint measurement\n\nEXAMPLES:\n- Single trial: nct_id='NCT03661411'\n- Phase 3 cancer endpoints: condition='cancer', phase=['PHASE3']\n- Recent diabetes outcomes: condition='diabetes', start_date_after='2022-01-01'",
   "input_schema": {
    "additionalProperties": false,
    "properties": {
     "condition": {
      "anyOf": [
       {
        "type": "string"
       },
       {
        "type": "null"
       }
      ],
      "default": null,
      "description": "Disease or therapeutic area for aggregate analysis. Examples: 'diabetes', 'Alzheimer', 'breast cancer', 'heart failure'. Required for aggregate analysis, optional if nct_id is provided."
     },
     "nct_id": {
      "anyOf": [
       {
        "type": "string"
       },
       {
        "type": "null"
       }
      ],
      "default": null,
      "description": "NCT ID for single trial analysis. Example: 'NCT03661411'. If provided, analyzes only this trial's endpoints. Either nct_id or condition must be provided."
     },
     "page_size": {
      "default": 50,
      "description": "Number of trials to analyze. Default 50. Use 100-200 for comprehensive analysis, 20-30 for quick overview. More trials = more representative but slower.",
      "maximum": 1000,
      "minimum": 1,
      "type": "integer"
     },
     "phase": {
      "anyOf": [
       {
        "type": "string"
       },
       {
        "items": {
         "enum": [
          "EARLY_PHASE1",
          "PHASE1",
          "PHASE2",
          "PHASE3",
          "PHASE4",
          "NA"
         ],
         "type": "string"
        },
        "type": "array"
       },
       {
        "type": "null"
       }
      ],
      "default": null,
      "description": "Filter by trial phase. Endpoints often differ by phase:\n- PHASE1/PHASE2: Often safety endpoints, biomarkers\n- PHASE3: Pivotal efficacy endpoints (most relevant for regulatory)\n- PHASE4: Real-world outcomes\nExample: ['PHASE3'] for registration-quality endpoints"
     },
     "start_date_after": {
      "anyOf": [
       {
        "type": "string"
       },
       {
        "type": "null"
       }
      ],
      "default": null,
      "description": "Only analyze trials started after this date. Format: YYYY-MM-DD. Useful for seeing modern/recent endpoint trends. Example: '2020-01-01' for trials from 2020 onwards."
     }
    },
    "type": "object"
   },
   "name": "analyze_endpoints",
   "output_schema": {
    "type": "object",
    "properties": {
     "trials_analyzed": {
      "type": "number"
     },
     "nct_id": {
      "type": "string"
     },
     "condition": {},
     "primary_endpoints": {
      "type": "array",
      "items": {
       "type": "object",
       "properties": {
        "measure": {
         "type": "string"
        },
        "time_frame": {
         "type": "string"
        },
        "description": {
         "type": "string"
        },
        "type": {
         "type": "string"
        }
       }
      }
     },
     "secondary_endpoints": {
      "type": "array",
      "items": {
       "type": "object",
       "properties": {
        "measure": {
         "type": "string"
        },
        "time_frame": {
         "type": "string"
        },
        "description": {
         "type": "string"
        },
        "type": {
         "type": "string"
        }
       }
      }
     },
     "other_endpoints": {
      "type": "array"
     },
     "common_measures": {
      "type": "array",
      "items": {
       "type": "string"
      }
     }
    }
   }
  },
  {
   "description": "Get comprehensive details for a specific clinical trial using its NCT ID.\n\nWHEN TO USE:\n- User provides a specific NCT ID (e.g., 'Tell me about NCT04567890')\n- Need full eligibility criteria, endpoints, or locations for a specific trial\n- Following up on a trial found via search_trials\n- Answering detailed questions about a known trial\n- Verifying patient eligibility for a specific trial\n\nUSE search_trials INSTEAD FOR:\n- Finding trials (this tool requires knowing the NCT ID)\n- Browsing trials by condition/intervention/sponsor\n\nWHAT THIS RETURNS:\n- Full eligibility criteria (inclusion/exclusion)\n- Study design and methodology\n- Primary, secondary, and other endpoints with timeframes\n- All study locations with contact info\n- Sponsor and collaborator details\n- Study dates and enrollment numbers\n- Results link if trial has published results\n\nNCT ID FORMAT: 'NCT' followed by 8 digits (e.g., NCT04567890, NCT00001234)",
   "input_schema": {
    "additionalProperties": false,
    "properties": {
     "nct_id": {
      "description": "NCT identifier for the clinical trial. Format: 'NCT' + 8 digits. Examples: 'NCT04567890', 'NCT00001234'. If user provides just the number, prepend 'NCT'. Case-insensitive.",
      "type": "string"
     }
    },
    "required": [
     "nct_id"
    ],
    "type": "object"
   },
   "name": "get_trial_details",
   "output_schema": {
    "type": "object",
    "properties": {
     "found": {
      "type": "boolean"
     },
     "trial": {
      "type": "object",
      "properties": {
       "nct_id": {
        "type": "string"
       },
       "title": {
        "type": "string"
       },
       "brief_title": {
        "type": "string"
       },
       "acronym": {},
       "status": {
        "type": "string"
       },
       "phase": {
        "type": "array",
        "items": {
         "type": "string"
        }
       },
       "study_type": {
        "type": "string"
       },
       "conditions": {
        "type": "array",
        "items": {
         "type": "string"
        }
       },
       "interventions": {
        "type": "array",
        "items": {
         "type": "string"
        }
       },
       "sponsor": {
        "type": "string"
       },
       "collaborators": {},
       "enrollment": {
        "type": "number"
       },
       "start_date": {
        "type": "string"
       },
       "primary_completion_date": {
        "type": "string"
       },
       "completion_date": {
        "type": "string"
       },
       "brief_summary": {
        "type": "string"
       },
       "detailed_description": {
        "type": "string"
       },
       "eligibility_criteria": {
        "type": "string"
       },
       "minimum_age": {
        "type": "string"
       },
       "maximum_age": {
        "type": "string"
       },
       "sex": {
        "type": "string"
       },
       "healthy_volunteers": {
        "type": "string"
       },
       "primary_outcomes": {
        "type": "array",
        "items": {
         "type": "object",
         "properties": {
          "measure": {
           "type": "string"
          },
          "time_frame": {
           "type": "string"
          },
          "description": {
           "type": "string"
          },
          "type": {
           "type": "string"
          }
         }
        }
       },
       "secondary_outcomes": {
        "type": "array",
        "items": {
         "type": "object",
         "properties": {
          "measure": {
           "type": "string"
          },
          "time_frame": {
           "type": "string"
          },
          "description": {
           "type": "string"
          },
          "type": {
           "type": "string"
          }
         }
        }
       },
       "other_outcomes": {},
       "locations": {
        "type": "array",
        "items": {
         "type": "object",
         "properties": {
          "facility": {
           "type": "string"
          },
          "city": {
           "type": "string"
          },
          "state": {
           "type": "string"
          },
          "country": {
           "type": "string"
          },
          "zip": {
           "type": "string"
          },
          "status": {},
          "contacts": {}
         }
        }
       },
       "url": {
        "type": "string"
       },
       "has_results": {
        "type": "boolean"
       }
      }
     }
    }
   }
  },
  {
   "description": "Find clinical trials matching specific patient eligibility criteria. Use this for patient-trial matching and finding trials a specific patient might qualify for.\n\nDEFAULT STATUS: Only searches RECRUITING trials. To include completed, upcoming, or all trials, explicitly set the status parameter.\n\nWHEN TO USE:\n- Patient matching: 'Find trials for a 65-year-old female with diabetes'\n- Specific criteria: 'Trials requiring HbA1c > 8%' or 'BRCA positive trials'\n- Age-restricted searches: 'Pediatric cancer trials' or 'Trials for elderly patients'\n- Finding trials by inclusion/exclusion criteria\n\nUSE search_trials FOR:\n- General disease/condition searches\n- When patient demographics don't matter\n\nELIGIBILITY KEYWORDS TIPS:\n- Use medical abbreviations: 'ECOG', 'HbA1c', 'BMI', 'eGFR'\n- Search criteria text: 'prior chemotherapy', 'treatment naive'\n- Biomarkers: 'BRCA mutation', 'HER2 positive', 'PD-L1'\n- Lab values: 'creatinine', 'ALT', 'bilirubin'\n\n- ICD-10 codes indicate specific subtypes (E10.x=Type 1, E11.x=Type 2, etc.)\n- Disease subtypes matter: Type 1 vs Type 2 diabetes, HER2+ vs HER2- cancer, etc.\nEXAMPLES:\n- '65yo diabetic patient' -> condition='diabetes', min_age='18 Years', max_age='70 Years'\n- 'Breast cancer with BRCA' -> condition='breast cancer', eligibility_keywords='BRCA'\n- 'Recruiting trials for men with prostate cancer' -> condition='prostate cancer', sex='MALE'",
   "input_schema": {
    "additionalProperties": false,
    "properties": {
     "condition": {
      "anyOf": [
       {
        "type": "string"
       },
       {
        "type": "null"
       }
      ],
      "default": null,
      "description": "Primary medical condition for the patient. Optional. Examples: 'diabetes', 'breast cancer', 'Alzheimer', 'heart failure'. Can be omitted if searching by other eligibility criteria only."
     },
     "eligibility_keywords": {
      "anyOf": [
       {
        "type": "string"
       },
       {
        "type": "null"
       }
      ],
      "default": null,
      "description": "Keywords to search in inclusion/exclusion criteria text. Examples: 'HbA1c > 8', 'BRCA mutation', 'ECOG 0-1', 'treatment naive', 'prior chemotherapy'. Searches the full eligibility criteria text for these terms."
     },
     "max_age": {
      "anyOf": [
       {
        "type": "string"
       },
       {
        "type": "null"
       }
      ],
      "default": null,
      "description": "Patient's age (upper bound for matching). Format: 'X Years' or 'X Months'. Examples: '75 Years', '12 Years'. Finds trials where the trial's MaximumAge requirement is at or above this value, meaning the patient meets the maximum age requirement."
     },
     "min_age": {
      "anyOf": [
       {
        "type": "string"
       },
       {
        "type": "null"
       }
      ],
      "default": null,
      "description": "Patient's age (lower bound for matching). Format: 'X Years' or 'X Months'. Examples: '18 Years', '65 Years', '6 Months'. Finds trials where the trial's MinimumAge requirement is at or below this value, meaning the patient meets the minimum age requirement."
     },
     "page_size": {
      "default": 10,
      "description": "Results per page. Default 10.",
      "maximum": 1000,
      "minimum": 1,
      "type": "integer"
     },
     "page_token": {
      "anyOf": [
       {
        "type": "string"
       },
       {
        "type": "null"
       }
      ],
      "default": null,
      "description": "Pagination token from previous response."
     },
     "sex": {
      "anyOf": [
       {
        "enum": [
         "ALL",
         "MALE",
         "FEMALE"
        ],
        "type": "string"
       },
       {
        "type": "null"
       }
      ],
      "default": null,
      "description": "Patient's sex for eligibility matching:\n- MALE: Find trials accepting male patients\n- FEMALE: Find trials accepting female patients\n- ALL: No sex restriction (default behavior if not specified)"
     },
     "status": {
      "anyOf": [
       {
        "type": "string"
       },
       {
        "items": {
         "enum": [
          "NOT_YET_RECRUITING",
          "RECRUITING",
          "ENROLLING_BY_INVITATION",
          "ACTIVE_NOT_RECRUITING",
          "COMPLETED",
          "SUSPENDED",
          "TERMINATED",
          "WITHDRAWN",
          "AVAILABLE",
          "NO_LONGER_AVAILABLE",
          "TEMPORARILY_NOT_AVAILABLE",
          "APPROVED_FOR_MARKETING",
          "WITHHELD",
          "UNKNOWN"
         ],
         "type": "string"
        },
        "type": "array"
       },
       {
        "type": "null"
       }
      ],
      "default": null,
      "description": "Trial recruitment status. Defaults to ['RECRUITING'] if not specified. For patient matching, usually want RECRUITING trials only. Add NOT_YET_RECRUITING to include upcoming trials."
     }
    },
    "type": "object"
   },
   "name": "search_by_eligibility",
   "output_schema": {
    "type": "object",
    "properties": {
     "count": {
      "type": "number"
     },
     "total": {},
     "next_page_token": {
      "type": "string"
     },
     "items": {
      "type": "array",
      "items": {
       "type": "object",
       "properties": {
        "nct_id": {
         "type": "string"
        },
        "title": {
         "type": "string"
        },
        "status": {
         "type": "string"
        },
        "phase": {
         "type": "array",
         "items": {
          "type": "string"
         }
        },
        "conditions": {
         "type": "array",
         "items": {
          "type": "string"
         }
        },
        "interventions": {
         "type": "array",
         "items": {
          "type": "string"
         }
        },
        "sponsor": {
         "type": "string"
        },
        "enrollment": {
         "type": "number"
        },
        "start_date": {
         "type": "string"
        },
        "primary_completion_date": {
         "type": "string"
        },
        "locations_count": {
         "type": "number"
        },
        "study_type": {
         "type": "string"
        }
       }
      }
     }
    }
   }
  },
  {
   "description": "Find all clinical trials sponsored by a specific company or organization.\nFunctionally equivalent to search_trials(sponsor=...).\n\nWHEN TO USE:\n- Questions about a company's pipeline (e.g., 'What is Pfizer working on?')\n- Competitive intelligence (e.g., 'What cancer drugs is Novartis developing?')\n- Tracking pharma company portfolios and development programs\n- Finding trials from academic institutions (e.g., 'Mayo Clinic', 'NIH')\n\nUSE search_trials INSTEAD FOR:\n- Disease-focused searches where sponsor doesn't matter\n- Finding trials by treatment name rather than sponsor\n\nEXAMPLES:\n- 'Pfizer Phase 3 trials' -> sponsor_name='Pfizer', phase=['PHASE3']\n- 'Moderna COVID vaccines' -> sponsor_name='Moderna', condition='COVID-19'\n- 'Active Merck oncology trials' -> sponsor_name='Merck', condition='cancer', status=['RECRUITING']\n\nTIPS:\n- Partial names work: 'Pfizer' matches 'Pfizer Inc', 'Pfizer Pharmaceuticals'\n- Set count_total=true to get total number of trials by sponsor\n- Combine with phase filter to see early vs late stage pipeline",
   "input_schema": {
    "additionalProperties": false,
    "properties": {
     "condition": {
      "anyOf": [
       {
        "type": "string"
       },
       {
        "type": "null"
       }
      ],
      "default": null,
      "description": "Filter by disease/condition to focus on a therapeutic area. Examples: 'cancer', 'diabetes', 'COVID-19', 'Alzheimer'. Useful for questions like 'What is Pfizer doing in oncology?'"
     },
     "count_total": {
      "default": false,
      "description": "Set true to get total count. Useful for 'How many trials does X sponsor?'",
      "type": "boolean"
     },
     "page_size": {
      "default": 10,
      "description": "Results per page. Use 50-100 for comprehensive pipeline analysis.",
      "maximum": 1000,
      "minimum": 1,
      "type": "integer"
     },
     "page_token": {
      "anyOf": [
       {
        "type": "string"
       },
       {
        "type": "null"
       }
      ],
      "default": null,
      "description": "Pagination token from previous response to get next page."
     },
     "phase": {
      "anyOf": [
       {
        "type": "string"
       },
       {
        "items": {
         "enum": [
          "EARLY_PHASE1",
          "PHASE1",
          "PHASE2",
          "PHASE3",
          "PHASE4",
          "NA"
         ],
         "type": "string"
        },
        "type": "array"
       },
       {
        "type": "null"
       }
      ],
      "default": null,
      "description": "Filter by development phase to analyze pipeline maturity:\n- PHASE1: Early development, safety focus\n- PHASE2: Mid-stage, efficacy testing\n- PHASE3: Late-stage, large trials before approval\n- PHASE4: Post-approval studies\nSelect multiple for broader view: ['PHASE2', 'PHASE3']"
     },
     "sponsor_name": {
      "description": "Company or organization name. Examples: 'Pfizer', 'Moderna', 'Novartis', 'NIH', 'Mayo Clinic'. Partial matches work (e.g., 'Pfizer' finds 'Pfizer Inc' and 'Pfizer Pharmaceuticals').",
      "type": "string"
     },
     "status": {
      "anyOf": [
       {
        "type": "string"
       },
       {
        "items": {
         "enum": [
          "NOT_YET_RECRUITING",
          "RECRUITING",
          "ENROLLING_BY_INVITATION",
          "ACTIVE_NOT_RECRUITING",
          "COMPLETED",
          "SUSPENDED",
          "TERMINATED",
          "WITHDRAWN",
          "AVAILABLE",
          "NO_LONGER_AVAILABLE",
          "TEMPORARILY_NOT_AVAILABLE",
          "APPROVED_FOR_MARKETING",
          "WITHHELD",
          "UNKNOWN"
         ],
         "type": "string"
        },
        "type": "array"
       },
       {
        "type": "null"
       }
      ],
      "default": null,
      "description": "Filter by trial status:\n- RECRUITING: Currently enrolling (active development)\n- COMPLETED: Finished trials (historical data)\n- ACTIVE_NOT_RECRUITING: Ongoing but closed to enrollment\n- TERMINATED: Stopped early (may indicate issues)"
     }
    },
    "required": [
     "sponsor_name"
    ],
    "type": "object"
   },
   "name": "search_by_sponsor",
   "output_schema": {
    "type": "object",
    "properties": {
     "count": {
      "type": "number"
     },
     "total": {},
     "next_page_token": {
      "type": "string"
     },
     "items": {
      "type": "array",
      "items": {
       "type": "object",
       "properties": {
        "nct_id": {
         "type": "string"
        },
        "title": {
         "type": "string"
        },
        "status": {
         "type": "string"
        },
        "phase": {
         "type": "array",
         "items": {
          "type": "string"
         }
        },
        "conditions": {
         "type": "array",
         "items": {
          "type": "string"
         }
        },
        "interventions": {
         "type": "array",
         "items": {
          "type": "string"
         }
        },
        "sponsor": {
         "type": "string"
        },
        "enrollment": {
         "type": "number"
        },
        "start_date": {
         "type": "string"
        },
        "primary_completion_date": {
         "type": "string"
        },
        "locations_count": {
         "type": "number"
        },
        "study_type": {
         "type": "string"
        }
       }
      }
     }
    }
   }
  },
  {
   "description": "Find principal investigators (PIs) and research sites conducting trials in a therapeutic area.\n\nWHEN TO USE:\n- 'Who are the leading researchers in Alzheimer trials?'\n- 'Find investigators at Mayo Clinic working on cancer'\n- 'Which sites in California are running diabetes trials?'\n- Site selection for planning new trials\n- Building investigator networks and collaborations\n\nUSE search_trials FOR:\n- Finding trials themselves rather than investigators\n- When you need trial details, not investigator info\n\nWHAT THIS RETURNS:\n- Investigator names and roles (Principal Investigator, Sub-Investigator)\n- Institutional affiliations\n- Facility/site names\n- Geographic locations\n- Associated trial NCT IDs and titles\n\nTIPS:\n- Use condition parameter to focus on a disease area\n- Add institution to find investigators at specific hospitals/universities\n- Use location for geographic focus (city, state, country)\n- Increase page_size to 50-100 for more comprehensive investigator lists\n- Use investigator_name for direct name search via advanced query syntax\n\nADVANCED: For direct investigator name search, use the investigator_name parameter which searches in OverallOfficialName and ResponsiblePartyInvestigatorFullName fields.",
   "input_schema": {
    "additionalProperties": false,
    "properties": {
     "condition": {
      "anyOf": [
       {
        "type": "string"
       },
       {
        "type": "null"
       }
      ],
      "default": null,
      "description": "Disease or therapeutic area to search. Optional. Examples: 'Alzheimer', 'breast cancer', 'diabetes', 'heart failure'. Finds investigators running trials in this area. Can be omitted if searching by institution or location only."
     },
     "institution": {
      "anyOf": [
       {
        "type": "string"
       },
       {
        "type": "null"
       }
      ],
      "default": null,
      "description": "Institution or facility name to filter by. Examples: 'Mayo Clinic', 'Duke University', 'MD Anderson', 'Johns Hopkins'. Takes precedence over location if both specified."
     },
     "investigator_name": {
      "anyOf": [
       {
        "type": "string"
       },
       {
        "type": "null"
       }
      ],
      "default": null,
      "description": "Direct search by investigator name. Examples: 'Smith', 'John Smith', 'Dr. Chen'. Searches in OverallOfficialName and ResponsiblePartyInvestigatorFullName fields. Use this when you know a specific investigator's name."
     },
     "location": {
      "anyOf": [
       {
        "type": "string"
       },
       {
        "type": "null"
       }
      ],
      "default": null,
      "description": "Geographic location to filter by. Examples: 'Boston', 'California', 'United States', 'Germany'. Use when institution is not specified."
     },
     "page_size": {
      "default": 20,
      "description": "Number of trials to analyze. More trials = more investigators found. Default 20. Use 50-100 for comprehensive investigator discovery.",
      "maximum": 1000,
      "minimum": 1,
      "type": "integer"
     },
     "status": {
      "anyOf": [
       {
        "type": "string"
       },
       {
        "items": {
         "enum": [
          "NOT_YET_RECRUITING",
          "RECRUITING",
          "ENROLLING_BY_INVITATION",
          "ACTIVE_NOT_RECRUITING",
          "COMPLETED",
          "SUSPENDED",
          "TERMINATED",
          "WITHDRAWN",
          "AVAILABLE",
          "NO_LONGER_AVAILABLE",
          "TEMPORARILY_NOT_AVAILABLE",
          "APPROVED_FOR_MARKETING",
          "WITHHELD",
          "UNKNOWN"
         ],
         "type": "string"
        },
        "type": "array"
       },
       {
        "type": "null"
       }
      ],
      "default": null,
      "description": "Filter by trial status. Default searches all statuses. Use ['RECRUITING'] to find currently active investigators."
     }
    },
    "type": "object"
   },
   "name": "search_investigators",
   "output_schema": {
    "type": "object",
    "properties": {
     "count": {
      "type": "number"
     },
     "trials_analyzed": {
      "type": "number"
     },
     "investigators": {
      "type": "array",
      "items": {
       "type": "object",
       "properties": {
        "name": {
         "type": "string"
        },
        "role": {
         "type": "string"
        },
        "affiliation": {
         "type": "string"
        },
        "facility": {
         "type": "string"
        },
        "location": {
         "type": "string"
        },
        "nct_id": {
         "type": "string"
        },
        "study_title": {
         "type": "string"
        },
        "condition": {
         "type": "string"
        }
       }
      }
     }
    }
   }
  },
  {
   "description": "Search ClinicalTrials.gov database for clinical trials. This is the PRIMARY tool for finding trials.\n\nWHEN TO USE:\n- Finding trials for a disease/condition (e.g., 'What trials exist for lung cancer?')\n- Finding trials testing a specific drug/treatment (e.g., 'Find pembrolizumab trials')\n- Finding trials in a geographic area (e.g., 'Clinical trials in Boston')\n- General trial discovery and research questions\n\nUSE DIFFERENT TOOLS FOR:\n- Detailed info on a specific trial by NCT ID -> use get_trial_details\n- All trials by a specific company -> use search_by_sponsor (or search_trials with sponsor=...)\n- Analyzing endpoints/outcomes -> use analyze_endpoints\n- Patient eligibility matching -> use search_by_eligibility\n\nQUERY SYNTAX (for condition, intervention, sponsor, location):\n- Boolean: 'cancer AND immunotherapy', 'aspirin OR ibuprofen', 'tumor NOT benign'\n- Exact phrase: '\"breast cancer\"' (with quotes)\n- Grouping: '(lung OR breast) AND cancer'\n- Synonyms are automatically included (e.g., 'heart attack' finds 'myocardial infarction')\n\nBEST PRACTICES:\n- Start with condition parameter for disease-focused searches\n- Add status=['RECRUITING'] to find active trials patients can join\n- Use phase filter for specific development stages (PHASE1, PHASE2, PHASE3, PHASE4)\n- Set count_total=true to know total matches (useful for: 'How many trials exist for X?')\n- Use page_size=50-100 for broader overviews, page_size=10 for quick lookups",
   "input_schema": {
    "additionalProperties": false,
    "properties": {
     "advanced_query": {
      "anyOf": [
       {
        "type": "string"
       },
       {
        "type": "null"
       }
      ],
      "default": null,
      "description": "Advanced query using Essie expression syntax. Only use when basic parameters are insufficient. Syntax: AREA[FieldName]value or AREA[FieldName]RANGE[min,max]. Examples:\n- Date filter: 'AREA[StartDate]RANGE[2023-01-01,MAX]' (trials started after Jan 2023)\n- Enrollment: 'AREA[EnrollmentCount]RANGE[100,MAX]' (100+ participants)\n- List size: 'AREA[Phase:size]2' (trials with exactly 2 phases)\n- Geo proximity: Use filter.geo parameter instead for distance-based searches"
     },
     "condition": {
      "anyOf": [
       {
        "type": "string"
       },
       {
        "type": "null"
       }
      ],
      "default": null,
      "description": "Disease or condition to search. This is the most common search parameter. Examples: 'diabetes', 'lung cancer', 'Alzheimer', 'COVID-19'. Supports Boolean operators: 'diabetes AND neuropathy', 'cancer NOT skin'. Use quotes for exact phrases: '\"type 2 diabetes\"'. Medical synonyms are automatically included in search."
     },
     "count_total": {
      "default": false,
      "description": "Set to true to get total count of matching trials. Useful for questions like 'How many trials exist for X?'. Slightly slower.",
      "type": "boolean"
     },
     "intervention": {
      "anyOf": [
       {
        "type": "string"
       },
       {
        "type": "null"
       }
      ],
      "default": null,
      "description": "Drug, treatment, or intervention name. Examples: 'pembrolizumab', 'metformin', 'CAR-T therapy', 'radiation'. Use OR for alternatives: 'aspirin OR ibuprofen OR naproxen'. Brand and generic names both work."
     },
     "location": {
      "anyOf": [
       {
        "type": "string"
       },
       {
        "type": "null"
       }
      ],
      "default": null,
      "description": "Geographic location for trial sites. Can be city, state, country, or region. Examples: 'Boston', 'California', 'United States', 'Germany', 'Europe'. Useful for finding trials patients can physically access."
     },
     "page_size": {
      "default": 10,
      "description": "Number of results per page. Default 10. Use 50-100 for comprehensive searches, 5-10 for quick lookups.",
      "maximum": 1000,
      "minimum": 1,
      "type": "integer"
     },
     "page_token": {
      "anyOf": [
       {
        "type": "string"
       },
       {
        "type": "null"
       }
      ],
      "default": null,
      "description": "Token from previous response's next_page_token to get next page. Do not set for first request."
     },
     "phase": {
      "anyOf": [
       {
        "type": "string"
       },
       {
        "items": {
         "enum": [
          "EARLY_PHASE1",
          "PHASE1",
          "PHASE2",
          "PHASE3",
          "PHASE4",
          "NA"
         ],
         "type": "string"
        },
        "type": "array"
       },
       {
        "type": "null"
       }
      ],
      "default": null,
      "description": "Filter by trial phase. Values:\n- EARLY_PHASE1: Initial safety testing\n- PHASE1: Safety and dosage testing in small groups\n- PHASE2: Efficacy and side effects testing\n- PHASE3: Large-scale efficacy confirmation\n- PHASE4: Post-market surveillance\n- NA: Not applicable (observational studies)\nCan select multiple: ['PHASE2', 'PHASE3']"
     },
     "sponsor": {
      "anyOf": [
       {
        "type": "string"
       },
       {
        "type": "null"
       }
      ],
      "default": null,
      "description": "Organization sponsoring or funding the trial. Examples: 'Pfizer', 'NIH', 'Novartis', 'Mayo Clinic'. For comprehensive sponsor analysis, use search_by_sponsor tool instead."
     },
     "status": {
      "anyOf": [
       {
        "type": "string"
       },
       {
        "items": {
         "enum": [
          "NOT_YET_RECRUITING",
          "RECRUITING",
          "ENROLLING_BY_INVITATION",
          "ACTIVE_NOT_RECRUITING",
          "COMPLETED",
          "SUSPENDED",
          "TERMINATED",
          "WITHDRAWN",
          "AVAILABLE",
          "NO_LONGER_AVAILABLE",
          "TEMPORARILY_NOT_AVAILABLE",
          "APPROVED_FOR_MARKETING",
          "WITHHELD",
          "UNKNOWN"
         ],
         "type": "string"
        },
        "type": "array"
       },
       {
        "type": "null"
       }
      ],
      "default": null,
      "description": "Filter by recruitment status. Common values:\n- RECRUITING: Actively enrolling patients (use this to find trials patients can join)\n- COMPLETED: Trial finished (use for historical research)\n- ACTIVE_NOT_RECRUITING: Ongoing but not enrolling\n- NOT_YET_RECRUITING: Approved but not started\n- TERMINATED/WITHDRAWN: Stopped early\nCan select multiple: ['RECRUITING', 'NOT_YET_RECRUITING']"
     },
     "study_type": {
      "anyOf": [
       {
        "enum": [
         "INTERVENTIONAL",
         "OBSERVATIONAL",
         "EXPANDED_ACCESS"
        ],
        "type": "string"
       },
       {
        "type": "null"
       }
      ],
      "default": null,
      "description": "Type of clinical study:\n- INTERVENTIONAL: Tests a treatment/intervention (most common for drug trials)\n- OBSERVATIONAL: Observes outcomes without intervention\n- EXPANDED_ACCESS: Provides experimental treatment outside trials"
     }
    },
    "type": "object"
   },
   "name": "search_trials",
   "output_schema": {
    "type": "object",
    "properties": {
     "count": {
      "type": "number"
     },
     "total": {
      "type": "number"
     },
     "next_page_token": {
      "type": "string"
     },
     "items": {
      "type": "array",
      "items": {
       "type": "object",
       "properties": {
        "nct_id": {
         "type": "string"
        },
        "title": {
         "type": "string"
        },
        "status": {
         "type": "string"
        },
        "phase": {},
        "conditions": {
         "type": "array",
         "items": {
          "type": "string"
         }
        },
        "interventions": {
         "type": "array",
         "items": {
          "type": "string"
         }
        },
        "sponsor": {
         "type": "string"
        },
        "enrollment": {
         "type": "number"
        },
        "start_date": {
         "type": "string"
        },
        "primary_completion_date": {
         "type": "string"
        },
        "locations_count": {
         "type": "number"
        },
        "study_type": {
         "type": "string"
        }
       }
      }
     }
    }
   }
  }
 ]
}
